{
  "$schema": "https://mintlify.com/schema.json",
  "name": "Baconz Plugins",
  "logo": {
    "light": "/logo/light.png",
    "dark": "/logo/dark.png"
  },
  "favicon": "/favicon.png",
  "colors": {
    "primary": "#0D9373",
    "light": "#07C983",
    "dark": "#0D9373",
    "anchors": "#0D9373"
  },
  "topbarLinks": [
    {
      "name": "Support",
      "url": "https://discord.com/invite/VQjTVKjs46"
    },
    {
      "name": "Spigot",
      "url": "https://www.spigotmc.org/members/mattbaconz.2410113/"
    },
    {
      "name": "Modrinth",
      "url": "https://modrinth.com/user/mattbaconz"
    }
  ],
  "topbarCtaButton": {
    "name": "Get Plugins",
    "url": "https://builtbybit.com/members/mattbaconz"
  },
  "tabs": [
    {
      "name": "Home",
      "url": "/"
    },
    {
      "name": "SeasonManager",
      "url": "seasonmanager"
    },
    {
      "name": "Pyramid",
      "url": "pyramid"
    }
  ],
  "navigation": [
    {
      "group": "General",
      "pages": [
        "index",
        "installation",
        "configuration",
        "commands",
        "placeholders"
      ]
    },
    {
      "group": "SeasonManager",
      "pages": [
        "seasonmanager/index",
        "seasonmanager/installation",
        "seasonmanager/configuration",
        "seasonmanager/commands",
        "seasonmanager/features"
      ]
    },
    {
      "group": "Pyramid",
      "pages": [
        "pyramid/index",
        "pyramid/installation",
        "pyramid/configuration",
        "pyramid/commands",
        "pyramid/permissions",
        "pyramid/features"
      ]
    }
  ],
  "footerSocials": {
    "discord": "https://discord.gg/yourdiscord",
    "github": "https://github.com/mattbaconz"
  }
}